frechetlib/__init__.py
frechetlib/continuous_frechet.py
frechetlib/data.py
frechetlib/discrete_frechet.py
frechetlib/frechet_utils.py
frechetlib/py.typed
frechetlib/retractable_frechet.py
frechetlib-0.1.1.dist-info/LICENSE
frechetlib-0.1.1.dist-info/METADATA
frechetlib-0.1.1.dist-info/WHEEL
frechetlib-0.1.1.dist-info/RECORD
