Metadata-Version: 2.1
Name: frechetlib
Version: 0.1.1
Summary: A package to compute distances between curves.
License: MIT
Author: Eliot Robson
Author-email: eliot.robson24@gmail.com
Requires-Python: >=3.10
Classifier: License :: OSI Approved :: MIT License
Classifier: Programming Language :: Python :: 3
Classifier: Programming Language :: Python :: 3.10
Classifier: Programming Language :: Python :: 3.11
Classifier: Programming Language :: Python :: 3.12
Requires-Dist: numba (>=0.58.1,<0.59.0)
Requires-Dist: numpy (>=1.26.3,<2.0.0)
Requires-Dist: pooch (>=1.8.1,<2.0.0)
Requires-Dist: scipy (>=1.11.4,<2.0.0)
Requires-Dist: typing-extensions (>=4.10.0,<5.0.0)
Project-URL: Homepage, https://github.com/eliotwrobson/FrechetLib
Project-URL: repository, https://github.com/eliotwrobson/FrechetLib
